nanosip/__init__.py
nanosip-0.0.7.dist-info/METADATA
nanosip-0.0.7.dist-info/WHEEL
nanosip-0.0.7.dist-info/licenses/LICENSE
nanosip-0.0.7.dist-info/RECORD
