Metadata-Version: 2.1
Name: nanosip
Version: 0.0.7
Summary: Simply ring a phone via SIP/VoIP
Project-URL: Homepage, https://github.com/philipp-fischer/nanosip
Project-URL: Documentation, https://github.com/philipp-fischer/nanosip
Project-URL: Repository, https://github.com/philipp-fischer/nanosip.git
Project-URL: Issues, https://github.com/philipp-fischer/nanosip/issues
Author-email: Philipp Fischer <me@phil.fm>
License-Expression: GPL-3.0-or-later
License-File: LICENSE
Keywords: call,sip,voip
Classifier: License :: OSI Approved :: GNU General Public License v3 or later (GPLv3+)
Classifier: Operating System :: OS Independent
Classifier: Programming Language :: Python :: 3
Requires-Python: >=3.8
